README.rst
setup.py
python_sudeste/__init__.py
python_sudeste/terceira_edicao.py
python_sudeste/third_edition.py
python_sudeste.egg-info/PKG-INFO
python_sudeste.egg-info/SOURCES.txt
python_sudeste.egg-info/dependency_links.txt
python_sudeste.egg-info/top_level.txt